{
	"variants": {
		"facing=north,half=lower": {
			"model": "dungeonsmod:block/urn_bottom"
		},
		"facing=north,half=upper": {
			"model": "dungeonsmod:block/urn_top"
		},
		"facing=east,half=lower": {
			"model": "dungeonsmod:block/urn_bottom",
			"y": 90
		},
		"facing=east,half=upper": {
			"model": "dungeonsmod:block/urn_top",
			"y": 90
		},
		"facing=south,half=lower": {
			"model": "dungeonsmod:block/urn_bottom",
			"y": 180
		},
		"facing=south,half=upper": {
			"model": "dungeonsmod:block/urn_top",
			"y": 180
		},
		"facing=west,half=lower": {
			"model": "dungeonsmod:block/urn_bottom",
			"y": 270
		},
		"facing=west,half=upper": {
			"model": "dungeonsmod:block/urn_top",
			"y": 270
		}
	}
}